{
  "id": "g_dome",
  "label": "穹顶",
  "name-en": "GDome",
  "description": "在 Geometry DSL 末尾追加 dome(radius,height) 一行，生成球冠/半球穹顶。",
  "description-en": "Append a `dome(radius,height)` line to the Geometry DSL, creating a spherical cap dome.",
  "version": "1.0.0",
  "autoIterate": true,
  "tags": ["geometry", "primitive", "dome", "cad"],
  "tag_labels": ["几何", "基础形状", "穹顶", "CAD"],
  "inputs": [
    { "name": "geometry", "type": "geometry", "required": false, "label": "几何" },
    { "name": "radius", "type": "number", "label": "球半径", "default": 0.5 },
    { "name": "height", "type": "number", "label": "球冠高度", "default": 0.5 },
    { "name": "id", "type": "string", "required": false, "label": "id", "default": "" }
  ],
  "outputs": [
    { "name": "geometry", "type": "geometry", "label": "几何" },
    { "name": "id", "type": "string", "label": "id" }
  ],
  "projectTypes": ["asset3d"]
}
