{
  "id": "terrain_smoother",
  "label": "地形平滑器",
  "description": "对地形网格进行细胞自动机平滑，使用 Moore 邻域多数投票规则消除孤立飞地，让地形边界更自然连通。",
  "description-en": "Smooths a terrain grid using cellular automaton majority voting (Moore neighborhood), eliminating isolated terrain patches.",
  "icon": "扁平插画风格小图标，左侧粗糙锯齿状地形色块，右侧经平滑后变为圆润流畅的色块轮廓，中间一个向右箭头，主色深绿和浅绿，简洁现代。",
  "version": "1.0.0",
  "tags": ["terrain", "smooth", "cellular-automata", "field"],
  "tag_labels": ["地形", "平滑", "细胞自动机", "野外"],
  "inputs": [
    {
      "name": "terrainGrid",
      "type": "grid",
      "label": "地形网格",
      "description": "待平滑的地形网格，1=水系，2=沙滩，3=草地",
      "description-en": "Input terrain grid to smooth: 1=water, 2=sand, 3=grass."
    },
    {
      "name": "iterations",
      "type": "number",
      "label": "平滑迭代次数",
      "description": "细胞自动机迭代轮数，越多越平滑但细节越少",
      "description-en": "Number of smoothing iterations; more iterations produce smoother but less detailed terrain.",
      "default": 2
    }
  ],
  "outputs": [
    {
      "name": "smoothedGrid",
      "type": "grid",
      "label": "平滑地形网格",
      "description": "平滑处理后的地形网格，值含义与输入相同",
      "description-en": "Smoothed terrain grid; same value encoding as input."
    }
  ]
}
