{
  "id": "organic_island_shape",
  "label": "有机海岸轮廓",
  "description": "基于柏林噪声与距离场算法，将输入网格列表中每个网格的非零区域重塑为有机岛屿轮廓，生成自然平滑的海岸线形状。支持单个网格输入，输出网格列表与海岛名称清单。",
  "description-en": "Uses Perlin noise and distance field to reshape each grid in the input list into a smooth organic island silhouette. Supports single grid input and outputs a list of grids with island name list.",
  "icon": "俯视岛屿轮廓，不规则有机海岸线与曲线海湾，蓝绿主色，外围深蓝海洋内部浅绿陆地。扁平插画风格，简洁小图标，主色2种。",
  "version": "2.0.0",
  "tags": ["island", "organic", "coastline", "perlin", "noise", "shape", "terrain", "procedural"],
  "tag_labels": ["岛屿", "有机形状", "海岸线", "柏林噪声", "噪声", "轮廓", "地形", "程序化"],
  "inputs": [
    {
      "name": "grids",
      "type": "array",
      "label": "输入网格列表",
      "description": "输入网格列表（array of grid），每个元素为一个矩形网格，非零区域作为岛屿生成的边界范围。也支持传入单个网格（自动包装为列表）。",
      "description-en": "Input list of grids; each grid's non-zero region is used as the bounding area. A single grid is also accepted and wrapped automatically."
    },
    {
      "name": "noiseScale",
      "type": "number",
      "label": "噪声频率",
      "description": "柏林噪声的空间频率，值越大海岸线弯曲细节越丰富，值越小海岸越平滑。建议范围 1~6。",
      "description-en": "Spatial frequency of Perlin noise; higher values create more jagged coastlines, lower values smoother ones. Recommended range: 1-6.",
      "default": 3
    },
    {
      "name": "noiseStrength",
      "type": "number",
      "label": "噪声强度",
      "description": "噪声对边界的扰动强度，0=完美椭圆，1=大幅扭曲边界。建议范围 0.1~0.5。",
      "description-en": "Noise perturbation strength: 0=perfect ellipse, 1=heavily distorted. Recommended range: 0.1-0.5.",
      "default": 0.35
    },
    {
      "name": "islandRatio",
      "type": "number",
      "label": "岛屿覆盖率",
      "description": "陆地面积占边界矩形的比例，0.3=小岛，0.6=较大岛屿。范围 0.2~0.75。",
      "description-en": "Fraction of the bounding box covered by land: 0.3=small island, 0.6=larger island. Range: 0.2-0.75.",
      "default": 0.5
    },
    {
      "name": "octaves",
      "type": "number",
      "label": "噪声层数",
      "description": "噪声叠加层数，层数越多细节越丰富（高频细节），建议 2~5。",
      "description-en": "Number of noise octaves; more octaves add finer coastal details. Recommended: 2-5.",
      "default": 4
    },
    {
      "name": "seed",
      "type": "number",
      "label": "随机种子",
      "description": "随机种子，0 使用当前时间。每个网格会在此基础上加偏移以保证形态各异。",
      "description-en": "Random seed; 0 uses current timestamp. Each grid gets an offset seed for unique shapes.",
      "default": 0
    }
  ],
  "outputs": [
    {
      "name": "outputGrids",
      "type": "array",
      "label": "岛屿轮廓网格列表",
      "description": "输出单值网格列表。每个输入网格产出4张网格，按顺序为：地面、浅水、中水、深水。每张网格中该层格子值为1，其余为0。",
      "description-en": "Output list of single-value grids. Each input grid yields 4 grids in order: land, shallow water, mid water, deep water. Active cells=1, others=0."
    },
    {
      "name": "nameList",
      "type": "array",
      "label": "名称清单",
      "description": "固定名称清单，包含四个条目：地面(id=1)、浅水(id=2)、中水(id=3)、深水(id=4)，type 均为 tile，与输出网格中的格子值一一对应。",
      "description-en": "Fixed name list with four entries: 地面(id=1), 浅水(id=2), 中水(id=3), 深水(id=4), all type=tile, matching cell values in the output grids."
    }
  ]
}
